app/__init__.py
app/my_util.py
commands/__init__.py
commands/__main__.py
commands/append_command.py
commands/const.py
commands/data.json_enc
commands/decrypt.py
commands/encrypt.py
commands/list_command.py
commands/run_command.py
commands/test.py
plx_false_positives/__init__.py
plx_false_positives/find_false_positives.py
plx_false_positives/test.py
samples/__init__.py
samples/list_samples.py
py_utils_khabibullin.m.m-0.0.37.dist-info/LICENSE.txt
py_utils_khabibullin.m.m-0.0.37.dist-info/METADATA
py_utils_khabibullin.m.m-0.0.37.dist-info/WHEEL
py_utils_khabibullin.m.m-0.0.37.dist-info/entry_points.txt
py_utils_khabibullin.m.m-0.0.37.dist-info/top_level.txt
py_utils_khabibullin.m.m-0.0.37.dist-info/RECORD
