Metadata-Version: 2.1
Name: py_utils_khabibullin.m.m
Version: 0.0.37
Summary: A small example package
Author-email: Marat Khabibullin <khabibullin.m.m@gmail.com>
License: Copyright (c) 2018 The Python Packaging Authority
Project-URL: Homepage, https://github.com/
Project-URL: Issues, https://github.com/
Classifier: Programming Language :: Python :: 3
Classifier: License :: OSI Approved :: MIT License
Classifier: Operating System :: OS Independent
Requires-Python: >=3.10
License-File: LICENSE.txt
Requires-Dist: prettytable >=3.9.0
Requires-Dist: pyperclip >=1.8.2
Requires-Dist: cryptography >=42.0.2
